hpdag/__init__.py
hpdag/dag.py
hpdag-0.2.dist-info/METADATA
hpdag-0.2.dist-info/WHEEL
hpdag-0.2.dist-info/top_level.txt
hpdag-0.2.dist-info/RECORD
