Metadata-Version: 2.1
Name: hpdag
Version: 0.2
Summary: A DAG library to manage hyperparameter search and ablations
Home-page: https://github.com/OhadRubin/hpdag
Author: Ohad Rubin
Requires-Dist: networkx
